sandwich_tag/__init__.py
sandwich_tag-0.1.0.dist-info/licenses/LICENSE
sandwich_tag-0.1.0.dist-info/METADATA
sandwich_tag-0.1.0.dist-info/WHEEL
sandwich_tag-0.1.0.dist-info/top_level.txt
sandwich_tag-0.1.0.dist-info/RECORD
