Metadata-Version: 2.4
Name: sandwich_tag
Version: 0.1.0
Summary: A django template tag that simplifies nested templates.
Author-email: Jacob Tumak <jacobtumak@users.noreply.github.com>
License: MIT License
Project-URL: Homepage, https://github.com/jacobtumak/sandwich
Project-URL: Repository, https://github.com/jacobtumak/sandwich
Keywords: sandwich,sandwich_tag,django-sandwich-tag
Classifier: Development Status :: 2 - Pre-Alpha
Classifier: License :: OSI Approved :: MIT License
Classifier: Intended Audience :: Developers
Classifier: Natural Language :: English
Classifier: Programming Language :: Python :: 3
Classifier: Framework :: Django
Requires-Python: <4.0,>=3.10
License-File: LICENSE
Requires-Dist: django
Dynamic: license-file
